{
  "project_info": {
    "project_number": "1038837150654",
    "firebase_url": "https://registroelectrocardiogramas-default-rtdb.europe-west1.firebasedatabase.app",
    "project_id": "registroelectrocardiogramas",
    "storage_bucket": "registroelectrocardiogramas.appspot.com"
  },
  "client": [
    {
      "client_info": {
        "mobilesdk_app_id": "1:1038837150654:android:9131469a7d0b9b5271ffef",
        "android_client_info": {
          "package_name": "com.example.segundo"
        }
      },
      "oauth_client": [
        {
          "client_id": "1038837150654-ql28o19o3mofk9qqb4g2iv36hipqhbpv.apps.googleusercontent.com",
          "client_type": 3
        }
      ],
      "api_key": [
        {
          "current_key": "AIzaSyAv_rz-SBhavu4jhQvZ4I24ngTc9-jdYak"
        }
      ],
      "services": {
        "appinvite_service": {
          "other_platform_oauth_client": [
            {
              "client_id": "1038837150654-ql28o19o3mofk9qqb4g2iv36hipqhbpv.apps.googleusercontent.com",
              "client_type": 3
            },
            {
              "client_id": "1038837150654-lh8ka2pn79dudvalvfnh9m6sq3q158ui.apps.googleusercontent.com",
              "client_type": 2,
              "ios_info": {
                "bundle_id": "felix.alvarez.Electrocargiogramas"
              }
            }
          ]
        }
      }
    }
  ],
  "configuration_version": "1"
}